4o periodo/LAB-SD_ufmg/LSD06/ula.vhd
-- Implementação de uma ULA de 8 bits
-- Para compilar e executar se desejar: certifique-se de ter o ghdl e gtkwave instalados primeiramente, e depois execute os comandos abaixo:
-- "ghdl -a *.vhd"
-- "ghdl -e funcao"
-- "ghdl -r tb_funcao --vcd=test.vcd"
-- "gtkwave test.vcd"

library ieee;
use ieee.std_logic_1164.all;
use ieee.numeric_std.all;

entity ula is 
    port (
        x, y : in std_logic_vector(7 downto 0); --entradas de 8 bits
        seletor : in std_logic_vector(2 downto 0); --seletor para identificar qual processo vai ser executado
        s : out std_logic_vector(7 downto 0)
    );
end entity;

architecture main of ula is 
    begin 

        my_proc : process(seletor) is 
        begin

            if(seletor = "000") then --operação de soma
                s <= std_logic_vector(unsigned(x) + unsigned(y)); 
            
            elsif(seletor = "001") then --operação de subtração
                s <= std_logic_vector(unsigned(x) + unsigned(y));
            
            elsif(seletor = "010") then --operação incremento
                s <= std_logic_vector(unsigned(x) + 1);
            
            elsif(seletor = "011") then --operação decremento
                s <= std_logic_vector(unsigned(x) - 1);

            elsif(seletor = "100") then --operação and
                s <= std_logic_vector(unsigned(x) and unsigned(y));
            
            elsif(seletor = "110") then --operação or
                s <= std_logic_vector(unsigned(x) or unsigned(y));
            
            elsif(seletor = "111") then --operação xor
                s <= std_logic_vector(unsigned(x) xor unsigned(y));
            
            else 
                s <= std_logic_vector(unsigned(x) or unsigned(y) srl 1);
            
            end if;

        end process;

end main;

4o periodo/LAB-SD_ufmg/LSD06/tb_ula.vhd
-- Testbench da ula de 8 bits

library ieee;
use ieee.std_logic_1164.all;
use ieee.numeric_std.all;

entity tb_ula is
    end tb_ula;

architecture main of tb_ula is 
    component ula is 
        port(
            x, y : in std_logic_vector(7 downto 0);
            seletor : in std_logic_vector(2 downto 0);
            s : out std_logic_vector(7 downto 0)
        );
end component;

    signal X, Y, S : std_logic_vector(7 downto 0);
    signal SELETOR : std_logic_vector(2 downto 0);

    begin 
        instancia_ula : ula port map(x => X, y => Y, seletor => SELETOR, s => S);

        x <= "00000001";
        y <= "00000111";
        seletor <= "000", "001" after 30 ns, "010" after 60 ns,
        "011" after 90 ns, "100" after 120 ns, "110" after 150 ns, "111" after 180 ns, "101" after 210 ns;

end main;

4o periodo/LAB-SD_ufmg/LSD06/test.vcd
$date
  Mon Apr 10 22:54:44 2023
$end
$version
  GHDL v0
$end
$timescale
  1 fs
$end
$scope module standard $end
$upscope $end
$scope module std_logic_1164 $end
$upscope $end
$scope module numeric_std $end
$upscope $end
$scope module tb_ula $end
$var reg 8 ! x[7:0] $end
$var reg 8 " y[7:0] $end
$var reg 8 # s[7:0] $end
$var reg 3 $ seletor[2:0] $end
$scope module instancia_ula $end
$var reg 8 % x[7:0] $end
$var reg 8 & y[7:0] $end
$var reg 3 ' seletor[2:0] $end
$var reg 8 ( s[7:0] $end
$upscope $end
$upscope $end
$enddefinitions $end
#0
b00000001 !
b00000111 "
b00001000 #
b000 $
b00000001 %
b00000111 &
b000 '
b00001000 (
#30000000
b001 $
b001 '
#60000000
b00000010 #
b010 $
b010 '
b00000010 (
#90000000
b00000000 #
b011 $
b011 '
b00000000 (
#120000000
b00000001 #
b100 $
b100 '
b00000001 (
#150000000
b00000111 #
b110 $
b110 '
b00000111 (
#180000000
b00000110 #
b111 $
b111 '
b00000110 (
#210000000
b00000011 #
b101 $
b101 '
b00000011 (
