4o periodo/LAB-SD_ufmg/LSD07/ex02/flipflopT.vhd
--Flip Flop tipo T
-- 'T- vem de 'toggle', que significa 'troca', 'inversao'
-- O output de um flip flop do tipo T é dependente tanto do input D quanto do atual valor da saída do flip flop
-- No flip flop tipo T, se o valor de t for 1 então o valor da saída irá inverter seu estado anterior 
-- se o valor de t for 0, então o valor da saída permanece em seu estado anterior

library ieee;
use ieee.std_logic_1164.all;

entity flipflop_t is 
    port (
        clk : in std_logic; -- clock
        reset : in std_logic; -- entrada de reset
        set : in std_logic; -- entrada do set
        t : in std_logic; -- entrada do flip flop
        q, q_barrado : out std_logic -- saida q
    );
    end entity;

architecture main of flipflop_t is 
    signal t_tmp : std_logic; -- sinal intermediário que é necessário no flip flop tipo T

    begin
    my_process : process(clk, reset, set)
        begin
            if(clk'event and clk='1') then 
                t_tmp <= t XOR t_tmp;
                q_barrado <= not (t XOR t_tmp);
            
            elsif(set = '0') then
                t_tmp <= '1';
                q_barrado <= '0';
            
            elsif(reset = '0') then
                t_tmp <= '1';
                q_barrado <= '0';
            
            end if;
        end process;
        q <= t_tmp; --atribuição final a saida 'q'
    end main;

4o periodo/LAB-SD_ufmg/LSD07/ex02/flipflopT_tb.vhd
library ieee;
use ieee.std_logic_1164.all;

entity flipflopT_tb is 
end entity;

architecture test of flipflopT_tb is 
    component flipflop_t is 
        port (
            clk : in std_logic;
            reset : in std_logic; -- entrada de reset
            set : in std_logic; -- entrada do preset
            t : in std_logic; -- entrada do flip flop
            q, q_barrado : out std_logic -- saida q
        );
    end component;

    signal CLK, RESET, SET, T, Q, Q_BARRADO : std_logic;

    begin
        instancia_flipflop_t : flipflop_t port map(clk => CLK, reset => RESET, set => SET,
        t => T, q => Q, q_barrado => Q_BARRADO);

        clk_generate : process
        begin
            while now < 1000 ns loop
                clk <= '0';
                wait for 30 ns;
                clk <= '1';
                wait for 30 ns;
                clk <= '0';
            end loop;
            wait;
        end process;
        
        reset_generate: process
        begin 
            reset <= '0';
            wait for 20 ns;
            reset <= '1';
            wait for 10 ns;
            reset <= '0';
            wait for 20 ns;
            wait;
        end process;

        set_generate: process
        begin 
            set <= '0';
            wait for 30 ns;
            set <= '1';
            wait for 20 ns;
            set <= '0';
            wait for 30 ns;
            wait;
        end process;

        entrada_generate: process 
        begin 
            t <= '1';
            wait for 10 ns;
            t <= '0';
            wait for 5 ns;
            t <= '1';
            wait for 10 ns;
            wait;
        end process;

end architecture;

4o periodo/LAB-SD_ufmg/LSD07/ex02/test.vcd
$date
  Mon Apr 17 20:13:53 2023
$end
$version
  GHDL v0
$end
$timescale
  1 fs
$end
$scope module standard $end
$upscope $end
$scope module std_logic_1164 $end
$upscope $end
$scope module flipflopt_tb $end
$var reg 1 ! clk $end
$var reg 1 " reset $end
$var reg 1 # set $end
$var reg 1 $ t $end
$var reg 1 % q $end
$var reg 1 & q_barrado $end
$scope module instancia_flipflop_t $end
$var reg 1 ' clk $end
$var reg 1 ( reset $end
$var reg 1 ) set $end
$var reg 1 * t $end
$var reg 1 + q $end
$var reg 1 , q_barrado $end
$var reg 1 - t_tmp $end
$upscope $end
$upscope $end
$enddefinitions $end
#0
0!
0"
0#
1$
1%
0&
0'
0(
0)
1*
1+
0,
1-
#10000000
0$
0*
#15000000
1$
1*
#20000000
1"
1(
#25000000
#30000000
1!
0"
1#
0%
1&
1'
0(
1)
0+
1,
0-
#50000000
0#
1%
0&
0)
1+
0,
1-
#60000000
0!
0'
#80000000
#90000000
1!
0%
1&
1'
0+
1,
0-
#120000000
0!
1%
0&
0'
1+
0,
1-
#150000000
1!
0%
1&
1'
0+
1,
0-
#180000000
0!
1%
0&
0'
1+
0,
1-
#210000000
1!
0%
1&
1'
0+
1,
0-
#240000000
0!
1%
0&
0'
1+
0,
1-
#270000000
1!
0%
1&
1'
0+
1,
0-
#300000000
0!
1%
0&
0'
1+
0,
1-
#330000000
1!
0%
1&
1'
0+
1,
0-
#360000000
0!
1%
0&
0'
1+
0,
1-
#390000000
1!
0%
1&
1'
0+
1,
0-
#420000000
0!
1%
0&
0'
1+
0,
1-
#450000000
1!
0%
1&
1'
0+
1,
0-
#480000000
0!
1%
0&
0'
1+
0,
1-
#510000000
1!
0%
1&
1'
0+
1,
0-
#540000000
0!
1%
0&
0'
1+
0,
1-
#570000000
1!
0%
1&
1'
0+
1,
0-
#600000000
0!
1%
0&
0'
1+
0,
1-
#630000000
1!
0%
1&
1'
0+
1,
0-
#660000000
0!
1%
0&
0'
1+
0,
1-
#690000000
1!
0%
1&
1'
0+
1,
0-
#720000000
0!
1%
0&
0'
1+
0,
1-
#750000000
1!
0%
1&
1'
0+
1,
0-
#780000000
0!
1%
0&
0'
1+
0,
1-
#810000000
1!
0%
1&
1'
0+
1,
0-
#840000000
0!
1%
0&
0'
1+
0,
1-
#870000000
1!
0%
1&
1'
0+
1,
0-
#900000000
0!
1%
0&
0'
1+
0,
1-
#930000000
1!
0%
1&
1'
0+
1,
0-
#960000000
0!
1%
0&
0'
1+
0,
1-
#990000000
1!
0%
1&
1'
0+
1,
0-
#1020000000
0!
1%
0&
0'
1+
0,
1-
